qntpy/__init__.py
qntpy/config.json
qntpy/constants.py
qntpy/currency.py
qntpy/information.py
qntpy/quantity.py
qntpy/us.py
qntpy-1.0.4.dist-info/METADATA
qntpy-1.0.4.dist-info/WHEEL
qntpy-1.0.4.dist-info/licenses/LICENSE
qntpy-1.0.4.dist-info/RECORD
