Metadata-Version: 2.1
Name: qntpy
Version: 1.0.4
Summary: a dimensional analysis module
Project-URL: Homepage, https://github.com/itsmiir/qpy
Project-URL: Bug Tracker, https://github.com/itsmiir/qpy/issues
Author-email: miir <itsmiir@outlook.com>
License-File: LICENSE
Classifier: Intended Audience :: Developers
Classifier: Intended Audience :: Education
Classifier: Intended Audience :: Science/Research
Classifier: License :: OSI Approved :: MIT License
Classifier: Operating System :: OS Independent
Classifier: Programming Language :: Python :: 3
Classifier: Topic :: Scientific/Engineering
Requires-Python: >=3.7
